README
setup.py
mdx_qrcode/QrCodeLib.py
mdx_qrcode/__init__.py
mdx_qrcode/extension.py
python_markdown_qrcode.egg-info/PKG-INFO
python_markdown_qrcode.egg-info/SOURCES.txt
python_markdown_qrcode.egg-info/dependency_links.txt
python_markdown_qrcode.egg-info/top_level.txt