Metadata-Version: 1.0
Name: python-markdown-qrcode
Version: 0.0.5.1
Summary: A markdown extension to insert qrcode datauri images based on supplied data.
Home-page: projects.airtonix.net/project/markdown-qrcode
Author: Zenobius Jiricek
Author-email: airtonix@gmail.com
License: LICENSE.md
Platform: UNKNOWN
